{"is_source_file": true, "format": "Kotlin", "description": "This file defines a Kotlin object 'StringUtils' providing utility functions 'join' and 'split' that work with a custom 'LinkedList' class, delegating the actual implementation to 'JoinUtils' and 'SplitUtils' respectively.", "external_files": ["org/example/list/LinkedList", "JoinUtils", "SplitUtils"], "external_methods": ["JoinUtils.join", "SplitUtils.split"], "published": ["StringUtils"], "classes": [], "methods": [{"name": "join", "description": "Concatenates elements of a LinkedList into a String using JoinUtils."}, {"name": "split", "description": "Splits a String into a LinkedList of substrings using SplitUtils."}], "calls": ["JoinUtils.join", "SplitUtils.split"], "search-terms": ["StringUtils", "join", "split", "LinkedList", "utilities", "org.example.utilities"], "state": 2, "file_id": 20, "knowledge_revision": 42, "git_revision": "72344d22337e711e1c61f35e9cb2cc2294b9b544", "hash": "d2e8b8a7116450b7d3a3224fee8ed988", "format-version": 4, "code-base-name": "android_frontend", "filename": "android_frontend/utilities/src/main/kotlin/org/example/utilities/StringUtils.kt", "revision_history": [{"42": "72344d22337e711e1c61f35e9cb2cc2294b9b544"}]}